scaleapi/__init__.py
scaleapi/_version.py
scaleapi/api.py
scaleapi/batches.py
scaleapi/evaluation_tasks.py
scaleapi/exceptions.py
scaleapi/files.py
scaleapi/projects.py
scaleapi/quality_tasks.py
scaleapi/studio.py
scaleapi/tasks.py
scaleapi/teams.py
scaleapi/training_tasks.py
scaleapi/api_client/__init__.py
scaleapi/api_client/v2/__init__.py
scaleapi/api_client/v2/api_client.py
scaleapi/api_client/v2/api_response.py
scaleapi/api_client/v2/configuration.py
scaleapi/api_client/v2/exceptions.py
scaleapi/api_client/v2/rest.py
scaleapi/api_client/v2/api/__init__.py
scaleapi/api_client/v2/api/v2_api.py
scaleapi/api_client/v2/models/__init__.py
scaleapi/api_client/v2/models/annotation.py
scaleapi/api_client/v2/models/annotation_boolean.py
scaleapi/api_client/v2/models/annotation_boolean_properties.py
scaleapi/api_client/v2/models/annotation_category.py
scaleapi/api_client/v2/models/annotation_category_multiple.py
scaleapi/api_client/v2/models/annotation_category_multiple_properties.py
scaleapi/api_client/v2/models/annotation_category_properties.py
scaleapi/api_client/v2/models/annotation_file.py
scaleapi/api_client/v2/models/annotation_file_properties.py
scaleapi/api_client/v2/models/annotation_file_properties_value.py
scaleapi/api_client/v2/models/annotation_integer.py
scaleapi/api_client/v2/models/annotation_integer_properties.py
scaleapi/api_client/v2/models/annotation_labeled_text.py
scaleapi/api_client/v2/models/annotation_labeled_text_properties.py
scaleapi/api_client/v2/models/annotation_metadata.py
scaleapi/api_client/v2/models/annotation_ranked_choices.py
scaleapi/api_client/v2/models/annotation_ranked_choices_properties.py
scaleapi/api_client/v2/models/annotation_ranked_groups.py
scaleapi/api_client/v2/models/annotation_ranked_groups_properties.py
scaleapi/api_client/v2/models/annotation_rubric_criteria.py
scaleapi/api_client/v2/models/annotation_rubric_criteria_properties.py
scaleapi/api_client/v2/models/annotation_rubric_rating.py
scaleapi-2.18.2.dist-info/LICENSE
scaleapi-2.18.2.dist-info/METADATA
scaleapi-2.18.2.dist-info/WHEEL
scaleapi-2.18.2.dist-info/top_level.txt
scaleapi-2.18.2.dist-info/RECORD
